prefect_github/__init__.py
prefect_github/_version.py
prefect_github/credentials.py
prefect_github/exceptions.py
prefect_github/graphql.py
prefect_github/mutations.py
prefect_github/organization.py
prefect_github/repository.py
prefect_github/repository_owner.py
prefect_github/user.py
prefect_github/utils.py
prefect_github/viewer.py
prefect_github/configs/mutation/add_comment.json
prefect_github/configs/mutation/add_pull_request_review.json
prefect_github/configs/mutation/add_reaction.json
prefect_github/configs/mutation/add_star.json
prefect_github/configs/mutation/close_issue.json
prefect_github/configs/mutation/close_pull_request.json
prefect_github/configs/mutation/create_issue.json
prefect_github/configs/mutation/create_pull_request.json
prefect_github/configs/mutation/remove_reaction.json
prefect_github/configs/mutation/remove_star.json
prefect_github/configs/mutation/request_reviews.json
prefect_github/configs/query/organization.json
prefect_github/configs/query/repository.json
prefect_github/configs/query/repository_owner.json
prefect_github/configs/query/user.json
prefect_github/configs/query/viewer.json
prefect_github/schemas/__init__.py
prefect_github/schemas/graphql_schema.json
prefect_github/schemas/graphql_schema.py
prefect_github-0.3.2.dist-info/licenses/LICENSE
prefect_github-0.3.2.dist-info/METADATA
prefect_github-0.3.2.dist-info/WHEEL
prefect_github-0.3.2.dist-info/entry_points.txt
prefect_github-0.3.2.dist-info/top_level.txt
prefect_github-0.3.2.dist-info/RECORD
